pytorch_bigtable/__init__.py
pytorch_bigtable/bigtable_dataset.py
pytorch_bigtable/pbt_C.cpython-39-x86_64-linux-gnu.so
pytorch_bigtable/row_range.py
pytorch_bigtable/row_set.py
pytorch_bigtable/version_filters.py
pytorch_bigtable/lib/libcrypto.so.10
pytorch_bigtable/lib/libssl.so.10
pytorch_bigtable-0.4.0.dist-info/LICENSE
pytorch_bigtable-0.4.0.dist-info/METADATA
pytorch_bigtable-0.4.0.dist-info/WHEEL
pytorch_bigtable-0.4.0.dist-info/top_level.txt
pytorch_bigtable-0.4.0.dist-info/RECORD
