Metadata-Version: 2.1
Name: pytorch-bigtable
Version: 0.4.0
Summary: Pytorch Extension for BigTable
Home-page: https://github.com/Unoperate/pytorch-cbt
Author: Google
Author-email: info@unoperate.com
License: UNKNOWN
Platform: UNKNOWN
Classifier: License :: OSI Approved :: Apache Software License
Classifier: Programming Language :: Python :: 3.6
Classifier: Programming Language :: Python :: 3.7
Classifier: Programming Language :: Python :: 3.8
Classifier: Programming Language :: Python :: 3.9
Classifier: Programming Language :: Python :: 3.10
Requires-Python: >=3.6
License-File: LICENSE
Requires-Dist: torch (>=1.10.0)
